MANIFEST.in
setup.py
HPPPM.egg-info/PKG-INFO
HPPPM.egg-info/SOURCES.txt
HPPPM.egg-info/dependency_links.txt
HPPPM.egg-info/requires.txt
HPPPM.egg-info/top_level.txt
hpppm/__init__.py
hpppm/demand_management.py
hpppm/error_handler.py
hpppm/ez_setup.py
hpppm/field_parser.py
hpppm/bin/hpppm_demand_management.py
hpppm/cfg/logging.conf
hpppm/data/addRequestNotes.data
hpppm/data/createRequest.data
hpppm/data/deleteRequests.data
hpppm/data/executeWFTransitions.data
hpppm/data/getRequests.data
hpppm/data/setRequestFields.data
hpppm/data/setRequestRemoteReferenceStatus.data
hpppm/logs/logconfig.log
hpppm/templates/addRequestNotes.xml
hpppm/templates/createRequest.xml
hpppm/templates/deleteRequests.xml
hpppm/templates/executeWFTransitions.xml
hpppm/templates/getRequests.xml
hpppm/templates/setRequestFields.xml
hpppm/templates/setRequestRemoteReferenceStatus.xml
hpppm/test/demand_management_tests.py
hpppm/test/error_handler_tests.py