Metadata-Version: 1.0
Name: HPPPM
Version: 0.1
Summary: Webservices API for HP Project and Portfolio Management
Home-page: http://pypi.python.org/pypi/HPPPM-Management/0.1
Author: Varun Juyal
Author-email: varunjuyal123@yahoo.com
License: PSF
Platform: UNKNOWN
